uniprot_m1_2024/__init__.py
uniprot_m1_2024/uniprot.py
uniprot_m1_2024/uniprot_collection.py
uniprot_m1_2024-2.0.0.dist-info/METADATA
uniprot_m1_2024-2.0.0.dist-info/WHEEL
uniprot_m1_2024-2.0.0.dist-info/top_level.txt
uniprot_m1_2024-2.0.0.dist-info/RECORD
