Metadata-Version: 2.1
Name: uniprot_m1_2024
Version: 2.0.0
Summary: Modélisation d'une fiche Uniprot et d'une collection d'objets Uniprot
Requires-Python: >=3.10
Requires-Dist: matplotlib>=3.9.2
